<?xml version="1.0" encoding="UTF-8"?>


<Levels>
    <Level levelName='Level_1' resourceFolder='Level_1' gamestate='GS_LEVEL_1'>
        <Gateway left='3866' top='1772' width='450' height='1150' destinationLevel='Level_2' dstPointX='500' dstPointY='500' active='0' requires="Note_1" reject="L1_NoExit"/>
    </Level>
    <Level levelName='Level_2' resourceFolder='Level_2' gamestate='GS_LEVEL_2'>
        <Gateway left='0' top='0' width='450' height='1150' destinationLevel='Level_1' dstPointX='3666' dstPointY='2408'/>
        <Gateway left='3666' top='1772' width='450' height='1150' destinationLevel='Level_3' dstPointX='500' dstPointY='500'/>
        <Gateway left='2520' top='0' width='1280' height='350' destinationLevel='Level_5' dstPointX='1232' dstPointY='2400'/>
    </Level>
    <Level levelName='Level_3' resourceFolder='Level_3' gamestate='GS_LEVEL_3'>
        <Gateway left='0' top='0' width='450' height='1150' destinationLevel='Level_2' dstPointX='3666' dstPointY='2408'/>
        <Gateway left='3666' top='1772' width='450' height='1150' destinationLevel='Level_4' dstPointX='350' dstPointY='2477' active='0' requires="birdSpokenTo" reject="L3_NoExit"/>
    </Level>
    <Level levelName='Level_4' resourceFolder='Level_4' gamestate='GS_LEVEL_4'>
        <Gateway left='0' top='2074' width='300' height='816' destinationLevel='Level_3' dstPointX='3666' dstPointY='2408'/>
        <Gateway left='2768' top='2088' width='334' height='394' destinationLevel='House' dstPointX='660' dstPointY='1612' active='0' requires="CombiLockOpened" reject="L4_H1Door"/>
        <Gateway left='2565' top='1376' width='391' height='364' destinationLevel='House_2' dstPointX='1120' dstPointY='2204'/>
        <Gateway left='677' top='410' width='426' height='393' destinationLevel='House_4' dstPointX='2584' dstPointY='2160' active='0' requires="RustyKey" reject="L4_H4Door"/>
    </Level>
    <Level levelName='Level_5' resourceFolder='Level_5' gamestate='GS_LEVEL_5'>
        <Gateway left='200' top='2456' width='1460' height='440' destinationLevel='Level_2' dstPointX='2436' dstPointY='420' active='0'/>
        <Gateway left='3392' top='0' width='712' height='1156' destinationLevel='Level_6' dstPointX='100' dstPointY='2200' active='0' requires="Daffodil"/>
    </Level>
    <Level levelName='Level_6' resourceFolder='Level_6' gamestate='GS_LEVEL_6'>
        <Gateway left='3688' top='1312' width='404' height='1212' destinationLevel='Level_7' dstPointX='428' dstPointY='1700'/>
    </Level>
    <Level levelName='Level_7' resourceFolder='Level_7' gamestate='GS_LEVEL_7'>
        <Gateway left='2944' top='612' width='1152' height='1200' destinationLevel='Falling' dstPointX='2048' dstPointY='1412'/>
    </Level>
    <Level levelName='Falling' resourceFolder='Falling' gamestate='GS_FALLING'>
    </Level>
    <Level levelName='pre-crowds' resourceFolder='Platform before crowds'>
        <Gateway left='3765' top='87' width='332' height='570' destinationLevel='Crowds' dstPointX='750' dstPointY='2208'/>
    </Level>
    <Level levelName='Crowds' resourceFolder='Crowds' gamestate='GS_CROWDS'>
        <Gateway left='3326' top='0' width='771' height='770' destinationLevel='Noise 1' dstPointX='367' dstPointY='2589'/>
    </Level>
    <Level levelName='Noise 1' resourceFolder='Noise_1'>
        <Gateway left='2129' top='2478' width='675' height='419' destinationLevel='Noise 2' dstPointX='2222' dstPointY='656'/>
        <Gateway left='1340' top='0' width='800' height='586' destinationLevel='Noise 3' dstPointX='1494' dstPointY='2278'/>
    </Level>
    <Level levelName='Noise 2' resourceFolder='Noise_2' gamestate='GS_NOISE_2'>
        <Gateway left='1956' top='0' width='810' height='524' destinationLevel='Noise 1' dstPointX='3208' dstPointY='2222'/>
    </Level>
    <Level levelName='Noise 3' resourceFolder='Noise_3' gamestate='GS_NOISE_3'>
        <Gateway left='1204' top='2300' width='908' height='738' destinationLevel='Noise 1' dstPointX='1332' dstPointY='672'/>
        <Gateway left='3317' top='195' width='480' height='311' destinationLevel='Eye room' dstPointX='2048' dstPointY='1000'/>
    </Level>
    <Level levelName='Eye room' resourceFolder='Eye room' gamestate='GS_EYE'>
    </Level>
    <Level levelName='Lead to final room' resourceFolder='Lead to FINAL'>
        <Gateway left='3387' top='441' width='509' height='441' destinationLevel='Final room' dstPointX='692' dstPointY='2420'/>
    </Level>
    <Level levelName='Final room' resourceFolder='FINAL room' gamestate='GS_FINAL'>
    </Level>
    <Level levelName='House' resourceFolder='Inside house' gamestate='GS_HOUSE_1'>
        <Gateway left='112' top='1308' width='248' height='724' destinationLevel='Level_4' dstPointX='2656' dstPointY='2300' active='0' requires="Note_5" reject="H1_NoExit"/>
    </Level>
    <Level levelName='House_2' resourceFolder='Inside house 2'>
        <Gateway left='140' top='2284' width='852' height='576' destinationLevel='Level_4' dstPointX='2346' dstPointY='1656' active='0' requires="Note_2" reject="H2_NoExit"/>
        <Gateway left='2936' top='108' width='752' height='616' destinationLevel='House_3' dstPointX='2844' dstPointY='984'/>
    </Level>
    <Level levelName='House_3' resourceFolder='Inside house 3'>
        <Gateway left='3068' top='896' width='568' height='452' destinationLevel='House_2' dstPointX='3720' dstPointY='1016' active='0' requires="Note_3" reject="H3_NoExit"/>
    </Level>
    <Level levelName='House_4' resourceFolder='Inside house 4'>
        <Gateway left='2901' top='2222' width='641' height='596' destinationLevel='Level_4' dstPointX='1122' dstPointY='815' active='0' requires="CalendarPage" reject="H4_NoExit"/>
    </Level>
</Levels>